{
  "ID": "f97e2a3c-dffd-4ce6-9fb5-1196c35c0202",
  "Version": "2.3.0.1",
  "Name": "uiGameOver",
  "Content": {
    "Content": {
      "Animation": {
        "Duration": 0,
        "Speed": 1.0,
        "Timelines": [],
        "ctype": "TimelineActionData"
      },
      "AnimationList": [],
      "ObjectData": {
        "Tag": 47,
        "Children": [
          {
            "SingleColor": {
              "R": 109,
              "G": 25,
              "B": 233
            },
            "FirstColor": {
              "R": 150,
              "G": 200
            },
            "EndColor": {},
            "ColorVector": {
              "ScaleY": 1.0
            },
            "Scale9Width": 1,
            "Scale9Height": 1,
            "TouchEnable": true,
            "AnchorPoint": {},
            "Position": {
              "X": 0.0,
              "Y": 0.0
            },
            "Scale": {
              "ScaleX": 1.0,
              "ScaleY": 1.0
            },
            "CColor": {},
            "IconVisible": false,
            "PrePosition": {
              "X": 0.0,
              "Y": 0.0
            },
            "PercentWidthEnable": true,
            "PercentHeightEnable": true,
            "PercentWidthEnabled": true,
            "PercentHeightEnabled": true,
            "PreSize": {
              "X": 1.0,
              "Y": 1.0
            },
            "Tag": 48,
            "Children": [
              {
                "FontSize": 48,
                "ButtonText": "分享此页",
                "FontResource": {
                  "Type": "Normal",
                  "Path": "hanyimanbu.ttf",
                  "Plist": ""
                },
                "TextColor": {},
                "DisabledFileData": {
                  "Type": "PlistSubImage",
                  "Path": "huikuangduanchu.png",
                  "Plist": "images.plist"
                },
                "PressedFileData": {
                  "Type": "PlistSubImage",
                  "Path": "huikuangduanchu.png",
                  "Plist": "images.plist"
                },
                "NormalFileData": {
                  "Type": "PlistSubImage",
                  "Path": "huikuangduanchu.png",
                  "Plist": "images.plist"
                },
                "Scale9Enable": true,
                "Scale9Width": 273,
                "Scale9Height": 96,
                "OutlineSize": 0,
                "ShadowOffsetX": 0,
                "ShadowOffsetY": 0,
                "TouchEnable": true,
                "AnchorPoint": {
                  "ScaleX": 0.5,
                  "ScaleY": 0.5
                },
                "Position": {
                  "X": 320.0055,
                  "Y": 122.0004
                },
                "Scale": {
                  "ScaleX": 1.0,
                  "ScaleY": 1.0
                },
                "CColor": {},
                "IconVisible": false,
                "PrePosition": {
                  "X": 0.5,
                  "Y": 0.1271
                },
                "PreSize": {
                  "X": 0.364,
                  "Y": 0.072
                },
                "HorizontalEdge": "BothEdge",
                "VerticalEdge": "BottomEdge",
                "LeftMargin": 183.5055,
                "RightMargin": 183.4945,
                "TopMargin": 789.9996,
                "BottomMargin": 74.0004,
                "Tag": 49,
                "ActionTag": -1616012025,
                "Size": {
                  "X": 273.0,
                  "Y": 96.0
                },
                "Name": "Button_share",
                "ctype": "ButtonObjectData"
              },
              {
                "FontSize": 48,
                "LabelText": "最高纪录\n",
                "FontResource": {
                  "Type": "Normal",
                  "Path": "hanyimanbu.ttf",
                  "Plist": ""
                },
                "OutlineSize": 0,
                "ShadowOffsetX": 0,
                "ShadowOffsetY": 0,
                "AnchorPoint": {
                  "ScaleX": 0.5,
                  "ScaleY": 0.5
                },
                "Position": {
                  "X": 328.7439,
                  "Y": 905.746
                },
                "Scale": {
                  "ScaleX": 1.0,
                  "ScaleY": 1.0
                },
                "CColor": {},
                "IconVisible": false,
                "PrePosition": {
                  "X": 0.5137,
                  "Y": 0.9435
                },
                "PreSize": {
                  "X": 0.0,
                  "Y": 0.0
                },
                "HorizontalEdge": "BothEdge",
                "VerticalEdge": "TopEdge",
                "LeftMargin": 232.7439,
                "RightMargin": 215.2561,
                "TopMargin": 30.254,
                "BottomMargin": 881.746,
                "Tag": 50,
                "ActionTag": 759776801,
                "Size": {
                  "X": 192.0,
                  "Y": 48.0
                },
                "Name": "Text_1_2",
                "ctype": "TextObjectData"
              },
              {
                "FontSize": 48,
                "ButtonText": "",
                "FontResource": {
                  "Type": "Normal",
                  "Path": "hanyimanbu.ttf",
                  "Plist": ""
                },
                "TextColor": {},
                "DisabledFileData": {
                  "Type": "PlistSubImage",
                  "Path": "zhucaidan.png",
                  "Plist": "images.plist"
                },
                "PressedFileData": {
                  "Type": "PlistSubImage",
                  "Path": "zhucaidan.png",
                  "Plist": "images.plist"
                },
                "NormalFileData": {
                  "Type": "PlistSubImage",
                  "Path": "zhucaidan.png",
                  "Plist": "images.plist"
                },
                "Scale9Enable": true,
                "Scale9Width": 96,
                "Scale9Height": 96,
                "OutlineSize": 0,
                "ShadowOffsetX": 0,
                "ShadowOffsetY": 0,
                "TouchEnable": true,
                "AnchorPoint": {
                  "ScaleX": 0.5,
                  "ScaleY": 0.5
                },
                "Position": {
                  "X": 77.9999,
                  "Y": 122.9992
                },
                "Scale": {
                  "ScaleX": 1.0,
                  "ScaleY": 1.0
                },
                "CColor": {},
                "IconVisible": false,
                "PrePosition": {
                  "X": 0.1219,
                  "Y": 0.1281
                },
                "PreSize": {
                  "X": 0.15,
                  "Y": 0.1
                },
                "HorizontalEdge": "LeftEdge",
                "VerticalEdge": "BottomEdge",
                "LeftMargin": 29.9999,
                "RightMargin": 514.0001,
                "TopMargin": 789.0008,
                "BottomMargin": 74.9992,
                "Tag": 52,
                "ActionTag": 1054817607,
                "Size": {
                  "X": 96.0,
                  "Y": 96.0
                },
                "Name": "Button_return",
                "ctype": "ButtonObjectData"
              },
              {
                "FileData": {
                  "Type": "PlistSubImage",
                  "Path": "huikuangduanchu.png",
                  "Plist": "images.plist"
                },
                "AnchorPoint": {
                  "ScaleX": 0.5,
                  "ScaleY": 0.5
                },
                "Position": {
                  "X": 534.7115,
                  "Y": 904.2861
                },
                "Scale": {
                  "ScaleX": 0.7,
                  "ScaleY": 0.7
                },
                "CColor": {},
                "IconVisible": false,
                "PrePosition": {
                  "X": 0.8355,
                  "Y": 0.942
                },
                "PreSize": {
                  "X": 0.0,
                  "Y": 0.0
                },
                "LeftMargin": 398.2115,
                "RightMargin": -31.2115,
                "TopMargin": 7.7139,
                "BottomMargin": 856.2861,
                "Tag": 59,
                "ActionTag": -402994472,
                "Size": {
                  "X": 273.0,
                  "Y": 96.0
                },
                "Name": "huikuangduanchu_3",
                "ctype": "SpriteObjectData"
              },
              {
                "FontSize": 48,
                "LabelText": "9999",
                "FontResource": {
                  "Type": "Normal",
                  "Path": "hanyimanbu.ttf",
                  "Plist": ""
                },
                "OutlineSize": 0,
                "ShadowOffsetX": 0,
                "ShadowOffsetY": 0,
                "AnchorPoint": {
                  "ScaleY": 0.5
                },
                "Position": {
                  "X": 488.0747,
                  "Y": 903.7437
                },
                "Scale": {
                  "ScaleX": 1.0,
                  "ScaleY": 1.0
                },
                "CColor": {},
                "IconVisible": false,
                "PrePosition": {
                  "X": 0.7626,
                  "Y": 0.9414
                },
                "PreSize": {
                  "X": 0.0,
                  "Y": 0.0
                },
                "HorizontalEdge": "BothEdge",
                "VerticalEdge": "TopEdge",
                "LeftMargin": 488.0747,
                "RightMargin": 55.9253,
                "TopMargin": 32.2563,
                "BottomMargin": 879.7437,
                "Tag": 51,
                "ActionTag": 1937840860,
                "Size": {
                  "X": 96.0,
                  "Y": 48.0
                },
                "Name": "Text_score",
                "ctype": "TextObjectData"
              },
              {
                "FileData": {
                  "Type": "PlistSubImage",
                  "Path": "xiaoxie.png",
                  "Plist": "images.plist"
                },
                "AnchorPoint": {
                  "ScaleX": 0.5,
                  "ScaleY": 0.5
                },
                "Position": {
                  "X": 62.5002,
                  "Y": 908.9995
                },
                "Scale": {
                  "ScaleX": 1.0,
                  "ScaleY": 1.0
                },
                "CColor": {},
                "IconVisible": false,
                "PrePosition": {
                  "X": 0.0977,
                  "Y": 0.9469
                },
                "PreSize": {
                  "X": 0.0,
                  "Y": 0.0
                },
                "LeftMargin": 19.5002,
                "RightMargin": 534.4998,
                "TopMargin": 22.5005,
                "BottomMargin": 880.4995,
                "Tag": 60,
                "ActionTag": 905902214,
                "Size": {
                  "X": 86.0,
                  "Y": 57.0
                },
                "Name": "xiaoxie_4",
                "ctype": "SpriteObjectData"
              },
              {
                "FileData": {
                  "Type": "PlistSubImage",
                  "Path": "huikuangduanchu.png",
                  "Plist": "images.plist"
                },
                "AnchorPoint": {
                  "ScaleX": 0.5,
                  "ScaleY": 0.5
                },
                "Position": {
                  "X": 320.0,
                  "Y": 460.8
                },
                "Scale": {
                  "ScaleX": 1.0,
                  "ScaleY": 1.0
                },
                "CColor": {},
                "IconVisible": false,
                "PositionPercentXEnabled": true,
                "PositionPercentYEnabled": true,
                "PrePosition": {
                  "X": 0.5,
                  "Y": 0.48
                },
                "PreSize": {
                  "X": 0.4266,
                  "Y": 0.1
                },
                "LeftMargin": 183.5,
                "RightMargin": 183.5,
                "TopMargin": 451.2,
                "BottomMargin": 412.8,
                "Tag": 61,
                "ActionTag": -395043991,
                "Size": {
                  "X": 273.0,
                  "Y": 96.0
                },
                "Name": "huikuangduanchu_5",
                "ctype": "SpriteObjectData"
              },
              {
                "FontSize": 14,
                "ButtonText": "",
                "TextColor": {
                  "R": 65,
                  "G": 65,
                  "B": 70
                },
                "DisabledFileData": {
                  "Type": "PlistSubImage",
                  "Path": "congxinkaishi.png",
                  "Plist": "images.plist"
                },
                "PressedFileData": {
                  "Type": "PlistSubImage",
                  "Path": "congxinkaishi.png",
                  "Plist": "images.plist"
                },
                "NormalFileData": {
                  "Type": "PlistSubImage",
                  "Path": "congxinkaishi.png",
                  "Plist": "images.plist"
                },
                "Scale9Enable": true,
                "Scale9Width": 96,
                "Scale9Height": 96,
                "OutlineSize": 0,
                "ShadowOffsetX": 0,
                "ShadowOffsetY": 0,
                "TouchEnable": true,
                "AnchorPoint": {
                  "ScaleX": 0.5,
                  "ScaleY": 0.5
                },
                "Position": {
                  "X": 562.0001,
                  "Y": 122.9992
                },
                "Scale": {
                  "ScaleX": 1.0,
                  "ScaleY": 1.0
                },
                "CColor": {},
                "IconVisible": false,
                "PrePosition": {
                  "X": 0.8781,
                  "Y": 0.1281
                },
                "PreSize": {
                  "X": 0.15,
                  "Y": 0.1
                },
                "HorizontalEdge": "BothEdge",
                "VerticalEdge": "BottomEdge",
                "LeftMargin": 514.0001,
                "RightMargin": 29.9999,
                "TopMargin": 789.0008,
                "BottomMargin": 74.9992,
                "Tag": 63,
                "ActionTag": -733272839,
                "Size": {
                  "X": 96.0,
                  "Y": 96.0
                },
                "Name": "Button_replay",
                "ctype": "ButtonObjectData"
              },
              {
                "FontSize": 48,
                "LabelText": "姓名",
                "FontResource": {
                  "Type": "Normal",
                  "Path": "hanyimanbu.ttf",
                  "Plist": ""
                },
                "OutlineSize": 0,
                "ShadowOffsetX": 0,
                "ShadowOffsetY": 0,
                "AnchorPoint": {
                  "ScaleX": 0.5,
                  "ScaleY": 0.5
                },
                "Position": {
                  "X": 320.0,
                  "Y": 460.8
                },
                "Scale": {
                  "ScaleX": 1.0,
                  "ScaleY": 1.0
                },
                "CColor": {},
                "IconVisible": false,
                "PositionPercentXEnabled": true,
                "PositionPercentYEnabled": true,
                "PrePosition": {
                  "X": 0.5,
                  "Y": 0.48
                },
                "PreSize": {
                  "X": 0.3406,
                  "Y": 0.0562
                },
                "LeftMargin": 272.0,
                "RightMargin": 272.0,
                "TopMargin": 475.2,
                "BottomMargin": 436.8,
                "Tag": 62,
                "ActionTag": 413334462,
                "Size": {
                  "X": 96.0,
                  "Y": 48.0
                },
                "Name": "Text_name",
                "ctype": "TextObjectData"
              },
              {
                "FontSize": 100,
                "LabelText": "太弱了",
                "FontResource": {
                  "Type": "Normal",
                  "Path": "hanyimanbu.ttf",
                  "Plist": ""
                },
                "OutlineSize": 0,
                "ShadowOffsetX": 0,
                "ShadowOffsetY": 0,
                "AnchorPoint": {
                  "ScaleX": 0.5,
                  "ScaleY": 0.5
                },
                "Position": {
                  "X": 320.0,
                  "Y": 341.8152
                },
                "Scale": {
                  "ScaleX": 1.0,
                  "ScaleY": 1.0
                },
                "CColor": {},
                "IconVisible": false,
                "PositionPercentXEnabled": true,
                "PositionPercentYEnabled": true,
                "PrePosition": {
                  "X": 0.5,
                  "Y": 0.3561
                },
                "PreSize": {
                  "X": 0.3406,
                  "Y": 0.0562
                },
                "LeftMargin": 170.0,
                "RightMargin": 170.0,
                "TopMargin": 568.1848,
                "BottomMargin": 291.8152,
                "Tag": 65,
                "ActionTag": 1209709259,
                "Size": {
                  "X": 300.0,
                  "Y": 100.0
                },
                "Name": "Text_title",
                "ctype": "TextObjectData"
              },
              {
                "FontSize": 48,
                "LabelText": "恭喜你征服了所有的地球生物",
                "FontResource": {
                  "Type": "Normal",
                  "Path": "hanyimanbu.ttf",
                  "Plist": ""
                },
                "HorizontalAlignmentType": "HT_Center",
                "OutlineSize": 0,
                "ShadowOffsetX": 0,
                "ShadowOffsetY": 0,
                "AnchorPoint": {
                  "ScaleX": 0.5,
                  "ScaleY": 0.5
                },
                "Position": {
                  "X": 320.0,
                  "Y": 232.0192
                },
                "Scale": {
                  "ScaleX": 1.0,
                  "ScaleY": 1.0
                },
                "CColor": {},
                "IconVisible": false,
                "PrePosition": {
                  "X": 0.5,
                  "Y": 0.2417
                },
                "PreSize": {
                  "X": 0.3406,
                  "Y": 0.0562
                },
                "HorizontalEdge": "BothEdge",
                "VerticalEdge": "BottomEdge",
                "LeftMargin": 8.0,
                "RightMargin": 8.0,
                "TopMargin": 703.9808,
                "BottomMargin": 208.0192,
                "Tag": 66,
                "ActionTag": -1744236164,
                "Size": {
                  "X": 624.0,
                  "Y": 48.0
                },
                "Name": "Text_tip",
                "ctype": "TextObjectData"
              },
              {
                "FileData": {
                  "Type": "Normal",
                  "Path": "xiangpiankuang.png",
                  "Plist": ""
                },
                "AnchorPoint": {
                  "ScaleX": 0.5,
                  "ScaleY": 0.5
                },
                "Position": {
                  "X": 300.8,
                  "Y": 681.6
                },
                "Scale": {
                  "ScaleX": 1.0,
                  "ScaleY": 1.0
                },
                "CColor": {},
                "IconVisible": false,
                "PrePosition": {
                  "X": 0.47,
                  "Y": 0.71
                },
                "PreSize": {
                  "X": 0.7031,
                  "Y": 0.3083
                },
                "HorizontalEdge": "BothEdge",
                "VerticalEdge": "TopEdge",
                "LeftMargin": 75.8,
                "RightMargin": 114.2,
                "TopMargin": 130.4,
                "BottomMargin": 533.6,
                "Tag": 53,
                "ActionTag": -1558426650,
                "Size": {
                  "X": 450.0,
                  "Y": 296.0
                },
                "Name": "Image_headbg",
                "ctype": "SpriteObjectData"
              },
              {
                "FileData": {
                  "Type": "Normal",
                  "Path": "face.png",
                  "Plist": ""
                },
                "AnchorPoint": {
                  "ScaleX": 0.5,
                  "ScaleY": 0.5
                },
                "Position": {
                  "X": 318.9976,
                  "Y": 676.4993
                },
                "Scale": {
                  "ScaleX": 1.0,
                  "ScaleY": 1.0
                },
                "CColor": {},
                "IconVisible": false,
                "PrePosition": {
                  "X": 0.4984,
                  "Y": 0.7047
                },
                "PreSize": {
                  "X": 0.4016,
                  "Y": 0.2667
                },
                "HorizontalEdge": "BothEdge",
                "VerticalEdge": "TopEdge",
                "LeftMargin": 190.4976,
                "RightMargin": 192.5024,
                "TopMargin": 155.5007,
                "BottomMargin": 548.4993,
                "Tag": 64,
                "ActionTag": 259831638,
                "Size": {
                  "X": 257.0,
                  "Y": 256.0
                },
                "Name": "Image_face",
                "ctype": "SpriteObjectData"
              }
            ],
            "ActionTag": -520743223,
            "Size": {
              "X": 640.0,
              "Y": 960.0
            },
            "Name": "Panel_root",
            "ctype": "PanelObjectData"
          }
        ],
        "Size": {
          "X": 640.0,
          "Y": 960.0
        },
        "Name": "Scene",
        "ctype": "SingleNodeObjectData"
      },
      "UsedResources": [
        "images.plist",
        "images.png",
        "face.png",
        "xiangpiankuang.png",
        "hanyimanbu.ttf"
      ],
      "ctype": "GameProjectData"
    }
  },
  "Type": "Scene"
}